our1314/__init__.py
our1314/halcon2opencv.py
our1314/halcon_templatematch.py
our1314/work.py
our1314-0.1.35.dist-info/LICENSE
our1314-0.1.35.dist-info/METADATA
our1314-0.1.35.dist-info/WHEEL
our1314-0.1.35.dist-info/top_level.txt
our1314-0.1.35.dist-info/RECORD
