Metadata-Version: 2.1
Name: our1314
Version: 0.1.35
Summary: a library for work
Home-page: https://github.com/our1314/our1314-python
Author: pp
Author-email: our1314@foxmail.com
License: MIT License
Keywords: our1314
Platform: any
License-File: LICENSE
